BEP032tools-0.3.32.dev0.data/data/README.md
BEP032tools-0.3.32.dev0.data/data/VERSION
BEP032tools-0.3.32.dev0.data/data/requirements.txt
BIDSTools/BidsDatatype.py
BIDSTools/BidsDirectoryStructure.py
BIDSTools/BidsEmptyRepositoryGenerator.py
BIDSTools/BidsEntity.py
BIDSTools/BidsFilestructure.py
BIDSTools/BidsModality.py
BIDSTools/CreatBIDSDataset.py
BIDSTools/Createdirectory.py
BIDSTools/Createfile.py
BIDSTools/__init__.py
BIDSTools/elabConf.json
BIDSTools/helper.py
BIDSTools/writing_agnosticfile.py
BIDSTools/ressources/__init__.py
BIDSTools/template_agnotic_file/CITATION.json
BIDSTools/template_agnotic_file/__init__.py
BIDSTools/template_agnotic_file/dataset_description.json
BIDSTools/template_agnotic_file/participants.json
BIDSTools/template_agnotic_file/samples.json
BIDSTools/tests/__init__.py
bep032/BEP032.py
bep032/Microscopy_bids_structure.py
bep032/Modality_agnostic_file.py
bep032/__init__.py
bep032/generator/__init__.py
bep032tools/__init__.py
bep032tools/rulesStructured.py
bep032tools/generator/BEP032Generator.py
bep032tools/generator/BEP032Templater.py
bep032tools/generator/__init__.py
bep032tools/generator/bidsconverter.py
bep032tools/generator/nwb2bidsgenerator.py
bep032tools/generator/utils.py
bep032tools/generator/tests/__init__.py
bep032tools/generator/tests/test_BEP032Generator.py
bep032tools/generator/tests/test_BEP032Templater.py
bep032tools/generator/tests/test_nwb2bidsgenerator.py
bep032tools/generator/tests/test_utils.py
bep032tools/generator/tests/utils.py
bep032tools/generator/tests/test_files/__init__.py
bep032tools/generator/tests/test_files/dummy.tsv
bep032tools/generator/tests/test_files/dummy_file.json
bep032tools/generator/tests/test_files/example.csv
bep032tools/generator/tests/test_files/example_1.csv
bep032tools/generator/tests/test_files/participants.tsv
bep032tools/validator/BEP032Validator.py
bep032tools/validator/__init__.py
bep032tools/validator/tests/__init__.py
bep032tools/validator/tests/test_BEP032Validator.py
BEP032tools-0.3.32.dev0.dist-info/LICENSE
BEP032tools-0.3.32.dev0.dist-info/METADATA
BEP032tools-0.3.32.dev0.dist-info/WHEEL
BEP032tools-0.3.32.dev0.dist-info/entry_points.txt
BEP032tools-0.3.32.dev0.dist-info/top_level.txt
BEP032tools-0.3.32.dev0.dist-info/RECORD
