Metadata-Version: 2.1
Name: BEP032tools
Version: 0.3.32.dev0
Summary: Checks the validity of a directory with respect to the BEP032 specifications 
Author: Jeremy Garcia, Sylvain Takerkart , Julia Sprenger
License: MIT
Requires-Python: >=3.7
License-File: LICENSE
Requires-Dist: pip ~=23.2.1
Requires-Dist: wheel ~=0.41.2
Requires-Dist: pytz ~=2024.1
Requires-Dist: PyYAML ~=6.0.1
Requires-Dist: numpy ~=1.26.4
Requires-Dist: setuptools ~=68.2.0
Requires-Dist: pandas ~=2.2.2
Requires-Dist: python-dateutil ~=2.9.0.post0
Requires-Dist: six ~=1.16.0
Requires-Dist: DigLabTools ~=0.0.4
Provides-Extra: test
Requires-Dist: pytest ; extra == 'test'
Requires-Dist: datalad ; extra == 'test'
Requires-Dist: parameterized ; extra == 'test'
Provides-Extra: tools
Requires-Dist: pandas ; extra == 'tools'
Requires-Dist: pynwb ; extra == 'tools'
Requires-Dist: neo ; extra == 'tools'
Requires-Dist: nixio ; extra == 'tools'
